TOPSIS_Vipul_101803491/__init__.py
TOPSIS_Vipul_101803491/vipul.py
TOPSIS_Vipul_101803491-1.3.dist-info/METADATA
TOPSIS_Vipul_101803491-1.3.dist-info/WHEEL
TOPSIS_Vipul_101803491-1.3.dist-info/license.txt
TOPSIS_Vipul_101803491-1.3.dist-info/top_level.txt
TOPSIS_Vipul_101803491-1.3.dist-info/RECORD
