Metadata-Version: 2.1
Name: TOPSIS-Vipul-101803491
Version: 1.3
Summary: TOPSIS implementation
Home-page: https://github.com/Vipul767/TOPSIS_Vipul_101803491
Author: Vipul Goel
Author-email: vgoel_be18@thapar.edu
License: MIT
Download-URL: https://github.com/Vipul767/TOPSIS_Vipul_101803491/archive/v_13.tar.gz
Keywords: TOSPSIS,Normalised_Matrix,Performance_score,Rank,Weighted_Normalised_matrix
Platform: UNKNOWN
Classifier: Development Status :: 3 - Alpha
Classifier: Intended Audience :: Developers
Classifier: Topic :: Software Development :: Build Tools
Classifier: License :: OSI Approved :: MIT License
Classifier: Programming Language :: Python :: 3
Classifier: Programming Language :: Python :: 3.4
Classifier: Programming Language :: Python :: 3.5
Classifier: Programming Language :: Python :: 3.6
Classifier: License :: OSI Approved :: MIT License
Requires-Dist: pandas
